```java
Classfile /Users/haining/mycodes/nothing/jdk1_8/src/main/java/com/tyning/jdk1_8/Test.class
  Last modified 2021-3-23; size 465 bytes
  MD5 checksum ea38302df04dae550e31b0e3d3cd745b
  Compiled from "Test.java"
public class com.tyning.jdk1_8.Test
  minor version: 0
  major version: 52
  flags: ACC_PUBLIC, ACC_SUPER
Constant pool:
   #1 = Methodref          #5.#15         // java/lang/Object."<init>":()V
   #2 = Fieldref           #16.#17        // java/lang/System.out:Ljava/io/PrintStream;
   #3 = Methodref          #18.#19        // java/io/PrintStream.println:(I)V
   #4 = Class              #20            // com/tyning/jdk1_8/Test
   #5 = Class              #21            // java/lang/Object
   #6 = Utf8               <init>
   #7 = Utf8               ()V
   #8 = Utf8               Code
   #9 = Utf8               LineNumberTable
  #10 = Utf8               main
  #11 = Utf8               ([Ljava/lang/String;)V
  #12 = Utf8               StackMapTable
  #13 = Utf8               SourceFile
  #14 = Utf8               Test.java
  #15 = NameAndType        #6:#7          // "<init>":()V
  #16 = Class              #22            // java/lang/System
  #17 = NameAndType        #23:#24        // out:Ljava/io/PrintStream;
  #18 = Class              #25            // java/io/PrintStream
  #19 = NameAndType        #26:#27        // println:(I)V
  #20 = Utf8               com/tyning/jdk1_8/Test
  #21 = Utf8               java/lang/Object
  #22 = Utf8               java/lang/System
  #23 = Utf8               out
  #24 = Utf8               Ljava/io/PrintStream;
  #25 = Utf8               java/io/PrintStream
  #26 = Utf8               println
  #27 = Utf8               (I)V
{
  public com.tyning.jdk1_8.Test();
    descriptor: ()V
    flags: ACC_PUBLIC
    Code:
      stack=1, locals=1, args_size=1
         0: aload_0
         1: invokespecial #1                  // Method java/lang/Object."<init>":()V
         4: return
      LineNumberTable:
        line 3: 0

  public static void main(java.lang.String[]);
    descriptor: ([Ljava/lang/String;)V
    flags: ACC_PUBLIC, ACC_STATIC
    Code:
      stack=2, locals=3, args_size=1
         0: iconst_0
         1: istore_1
         2: iconst_0
         3: istore_2
         4: iload_2
         5: bipush        50
         7: if_icmpge     21
        10: iload_1
        11: iinc          1, 1
        14: istore_1
        15: iinc          2, 1
        18: goto          4
        21: getstatic     #2                  // Field java/lang/System.out:Ljava/io/PrintStream;
        24: iload_1
        25: invokevirtual #3                  // Method java/io/PrintStream.println:(I)V
        28: return
      LineNumberTable:
        line 22: 0
        line 23: 2
        line 24: 10
        line 23: 15
        line 26: 21
        line 61: 28
      StackMapTable: number_of_entries = 2
        frame_type = 253 /* append */
          offset_delta = 4
          locals = [ int, int ]
        frame_type = 250 /* chop */
          offset_delta = 16
}

```



```java
Classfile /Users/haining/mycodes/nothing/jdk1_8/src/main/java/com/tyning/jdk1_8/Test.class
  Last modified 2021-3-23; size 465 bytes
  MD5 checksum ea38302df04dae550e31b0e3d3cd745b
  Compiled from "Test.java"
public class com.tyning.jdk1_8.Test
  minor version: 0
  major version: 52
  flags: ACC_PUBLIC, ACC_SUPER
Constant pool:
   #1 = Methodref          #5.#15         // java/lang/Object."<init>":()V
   #2 = Fieldref           #16.#17        // java/lang/System.out:Ljava/io/PrintStream;
   #3 = Methodref          #18.#19        // java/io/PrintStream.println:(I)V
   #4 = Class              #20            // com/tyning/jdk1_8/Test
   #5 = Class              #21            // java/lang/Object
   #6 = Utf8               <init>
   #7 = Utf8               ()V
   #8 = Utf8               Code
   #9 = Utf8               LineNumberTable
  #10 = Utf8               main
  #11 = Utf8               ([Ljava/lang/String;)V
  #12 = Utf8               StackMapTable
  #13 = Utf8               SourceFile
  #14 = Utf8               Test.java
  #15 = NameAndType        #6:#7          // "<init>":()V
  #16 = Class              #22            // java/lang/System
  #17 = NameAndType        #23:#24        // out:Ljava/io/PrintStream;
  #18 = Class              #25            // java/io/PrintStream
  #19 = NameAndType        #26:#27        // println:(I)V
  #20 = Utf8               com/tyning/jdk1_8/Test
  #21 = Utf8               java/lang/Object
  #22 = Utf8               java/lang/System
  #23 = Utf8               out
  #24 = Utf8               Ljava/io/PrintStream;
  #25 = Utf8               java/io/PrintStream
  #26 = Utf8               println
  #27 = Utf8               (I)V
{
  public com.tyning.jdk1_8.Test();
    descriptor: ()V
    flags: ACC_PUBLIC
    Code:
      stack=1, locals=1, args_size=1
         0: aload_0
         1: invokespecial #1                  // Method java/lang/Object."<init>":()V
         4: return
      LineNumberTable:
        line 3: 0

  public static void main(java.lang.String[]);
    descriptor: ([Ljava/lang/String;)V
    flags: ACC_PUBLIC, ACC_STATIC
    Code:
      stack=2, locals=3, args_size=1
         0: iconst_0
         1: istore_1
         2: iconst_0
         3: istore_2
         4: iload_2
         5: bipush        50
         7: if_icmpge     21
        10: iload_1
        11: iinc          1, 1
        14: istore_1
        15: iinc          2, 1
        18: goto          4
        21: getstatic     #2                  // Field java/lang/System.out:Ljava/io/PrintStream;
        24: iload_1
        25: invokevirtual #3                  // Method java/io/PrintStream.println:(I)V
        28: return
      LineNumberTable:
        line 22: 0
        line 23: 2
        line 24: 10
        line 23: 15
        line 26: 21
        line 61: 28
      StackMapTable: number_of_entries = 2
        frame_type = 253 /* append */
          offset_delta = 4
          locals = [ int, int ]
        frame_type = 250 /* chop */
          offset_delta = 16
}
SourceFile: "Test.java"

```

要说明问题的前提：计算机要进行计算的话从寄存器取值，然后进行计算。

还有就是代码中的变量存储的地方。如果想要进行计算的话就直接将存变量的变量值直接加载到寄存器上然后进行计算。

那么 i++ 和 ++i的执行过程就是：iload 和 iinc的先后顺序，iinc是在存储地方发生加法然后就是